rhiza_tools/__init__.py
rhiza_tools/__main__.py
rhiza_tools/cli.py
rhiza_tools/commands/__init__.py
rhiza_tools/commands/bump.py
rhiza_tools-0.1.1.dist-info/METADATA
rhiza_tools-0.1.1.dist-info/WHEEL
rhiza_tools-0.1.1.dist-info/entry_points.txt
rhiza_tools-0.1.1.dist-info/RECORD
