Metadata-Version: 2.4
Name: rhiza-tools
Version: 0.1.1
Summary: Add your description here
Requires-Python: >=3.11
Requires-Dist: loguru>=0.7.3
Requires-Dist: questionary>=2.1.1
Requires-Dist: semver>=3.0.4
Requires-Dist: tomlkit>=0.13.3
Requires-Dist: typer>=0.9.0
Provides-Extra: dev
Requires-Dist: marimo==0.18.4; extra == 'dev'
Requires-Dist: pdoc>=16.0.0; extra == 'dev'
Requires-Dist: pre-commit==4.5.1; extra == 'dev'
Requires-Dist: pytest-cov>=7.0.0; extra == 'dev'
Requires-Dist: pytest-html>=4.1.1; extra == 'dev'
Requires-Dist: pytest>=9.0.2; extra == 'dev'
Requires-Dist: python-dotenv==1.2.1; extra == 'dev'
